[
  {
    "id": "202604160851170001",
    "source": "野狐",
    "path": "/weiqi-page/replay.html?data=/weiqi-page/games/2026-04-15/野狐/game_202604160851170001.json",
    "black": "孙一格",
    "white": "王楚轩",
    "black_rank": "P5段",
    "white_rank": "P8段",
    "result": "W+R",
    "result_cn": "白中盘胜",
    "event": "衢州葛道职业训练赛<绝艺讲解>"
  },
  {
    "id": "202604160851170002",
    "source": "野狐",
    "path": "/weiqi-page/replay.html?data=/weiqi-page/games/2026-04-15/野狐/game_202604160851170002.json",
    "black": "金禹丞",
    "white": "심재익",
    "black_rank": "P9段",
    "white_rank": "P7段",
    "result": "B+R",
    "result_cn": "黑中盘胜",
    "event": "第4届烂柯杯世界公开赛32强<绝艺讲解>"
  },
  {
    "id": "202604160851170003",
    "source": "野狐",
    "path": "/weiqi-page/replay.html?data=/weiqi-page/games/2026-04-15/野狐/game_202604160851170003.json",
    "black": "党毅飞",
    "white": "范廷钰",
    "black_rank": "P9段",
    "white_rank": "P9段",
    "result": "B+R",
    "result_cn": "黑中盘胜",
    "event": "第4届烂柯杯世界公开赛32强<绝艺讲解>"
  },
  {
    "id": "202604160851170004",
    "source": "野狐",
    "path": "/weiqi-page/replay.html?data=/weiqi-page/games/2026-04-15/野狐/game_202604160851170004.json",
    "black": "张歆宇",
    "white": "金明训",
    "black_rank": "P6段",
    "white_rank": "P9段",
    "result": "W+R",
    "result_cn": "白中盘胜",
    "event": "第4届烂柯杯世界公开赛32强<绝艺讲解>"
  },
  {
    "id": "202604160851170005",
    "source": "野狐",
    "path": "/weiqi-page/replay.html?data=/weiqi-page/games/2026-04-15/野狐/game_202604160851170005.json",
    "black": "王元均",
    "white": "戎毅",
    "black_rank": "P9段",
    "white_rank": "P8段",
    "result": "B+R",
    "result_cn": "黑中盘胜",
    "event": "第4届烂柯杯世界公开赛32强<绝艺讲解>"
  },
  {
    "id": "202604160851170006",
    "source": "野狐",
    "path": "/weiqi-page/replay.html?data=/weiqi-page/games/2026-04-15/野狐/game_202604160851170006.json",
    "black": "上野愛咲美",
    "white": "藤沢里菜",
    "black_rank": "P6段",
    "white_rank": "P7段",
    "result": "B+2.50",
    "result_cn": "黑胜2.50目",
    "event": "第37期日本女流名人战挑战赛2/3局<绝艺讲解>"
  },
  {
    "id": "202604160851170007",
    "source": "野狐",
    "path": "/weiqi-page/replay.html?data=/weiqi-page/games/2026-04-15/野狐/game_202604160851170007.json",
    "black": "丁浩",
    "white": "李维清",
    "black_rank": "P9段",
    "white_rank": "P9段",
    "result": "B+R",
    "result_cn": "黑中盘胜",
    "event": "第4届烂柯杯世界公开赛32强<绝艺讲解>"
  },
  {
    "id": "202604160851170008",
    "source": "野狐",
    "path": "/weiqi-page/replay.html?data=/weiqi-page/games/2026-04-15/野狐/game_202604160851170008.json",
    "black": "邱禹然",
    "white": "赖均辅",
    "black_rank": "P7段",
    "white_rank": "P9段",
    "result": "W+R",
    "result_cn": "白中盘胜",
    "event": "第4届烂柯杯世界公开赛32强<绝艺讲解>"
  },
  {
    "id": "202604160851170009",
    "source": "野狐",
    "path": "/weiqi-page/replay.html?data=/weiqi-page/games/2026-04-15/野狐/game_202604160851170009.json",
    "black": "谢尔豪",
    "white": "陈祈睿",
    "black_rank": "P9段",
    "white_rank": "P9段",
    "result": "W+0.25",
    "result_cn": "白胜0.25目",
    "event": "第4届烂柯杯世界公开赛32强<绝艺讲解>"
  },
  {
    "id": "202604160851170010",
    "source": "野狐",
    "path": "/weiqi-page/replay.html?data=/weiqi-page/games/2026-04-15/野狐/game_202604160851170010.json",
    "black": "申真谞",
    "white": "谢科",
    "black_rank": "P9段",
    "white_rank": "P9段",
    "result": "B+R",
    "result_cn": "黑中盘胜",
    "event": "第4届烂柯杯世界公开赛32强<张学斌＆夏夏＆绝艺解说>"
  },
  {
    "id": "202604160851170011",
    "source": "野狐",
    "path": "/weiqi-page/replay.html?data=/weiqi-page/games/2026-04-15/野狐/game_202604160851170011.json",
    "black": "朴廷桓",
    "white": "陶欣然",
    "black_rank": "P9段",
    "white_rank": "P9段",
    "result": "B+R",
    "result_cn": "黑中盘胜",
    "event": "第4届烂柯杯世界公开赛32强<绝艺讲解>"
  },
  {
    "id": "202604160851180012",
    "source": "野狐",
    "path": "/weiqi-page/replay.html?data=/weiqi-page/games/2026-04-15/野狐/game_202604160851180012.json",
    "black": "范胤",
    "white": "이지현M",
    "black_rank": "P9段",
    "white_rank": "P9段",
    "result": "W+R",
    "result_cn": "白中盘胜",
    "event": "第4届烂柯杯世界公开赛32强<绝艺讲解>"
  },
  {
    "id": "202604160851180013",
    "source": "野狐",
    "path": "/weiqi-page/replay.html?data=/weiqi-page/games/2026-04-15/野狐/game_202604160851180013.json",
    "black": "杨鼎新",
    "white": "杨楷文",
    "black_rank": "P9段",
    "white_rank": "P9段",
    "result": "W+R",
    "result_cn": "白中盘胜",
    "event": "第4届烂柯杯世界公开赛32强<绝艺讲解>"
  },
  {
    "id": "202604160851180014",
    "source": "野狐",
    "path": "/weiqi-page/replay.html?data=/weiqi-page/games/2026-04-15/野狐/game_202604160851180014.json",
    "black": "申旻埈",
    "white": "夏晨琨",
    "black_rank": "P9段",
    "white_rank": "P8段",
    "result": "B+R",
    "result_cn": "黑中盘胜",
    "event": "第4届烂柯杯世界公开赛32强<绝艺讲解>"
  },
  {
    "id": "202604160851180015",
    "source": "野狐",
    "path": "/weiqi-page/replay.html?data=/weiqi-page/games/2026-04-15/野狐/game_202604160851180015.json",
    "black": "王星昊",
    "white": "廖元赫",
    "black_rank": "P9段",
    "white_rank": "P9段",
    "result": "W+0.25",
    "result_cn": "白胜0.25目",
    "event": "第4届烂柯杯世界公开赛32强<绝艺讲解>"
  },
  {
    "id": "202604160851180016",
    "source": "野狐",
    "path": "/weiqi-page/replay.html?data=/weiqi-page/games/2026-04-15/野狐/game_202604160851180016.json",
    "black": "李元荣",
    "white": "江维杰",
    "black_rank": "P9段",
    "white_rank": "P9段",
    "result": "W+R",
    "result_cn": "白中盘胜",
    "event": "第4届烂柯杯世界公开赛32强<绝艺讲解>"
  },
  {
    "id": "202604160851180017",
    "source": "野狐",
    "path": "/weiqi-page/replay.html?data=/weiqi-page/games/2026-04-15/野狐/game_202604160851180017.json",
    "black": "陈玉侬",
    "white": "连笑",
    "black_rank": "P8段",
    "white_rank": "P9段",
    "result": "B+R",
    "result_cn": "黑中盘胜",
    "event": "第4届烂柯杯世界公开赛32强<绝艺讲解>"
  },
  {
    "id": "202604160851180018",
    "source": "野狐",
    "path": "/weiqi-page/replay.html?data=/weiqi-page/games/2026-04-15/野狐/game_202604160851180018.json",
    "black": "卞相壹",
    "white": "许嘉阳",
    "black_rank": "P9段",
    "white_rank": "P9段",
    "result": "B+R",
    "result_cn": "黑中盘胜",
    "event": "第4届烂柯杯世界公开赛32强<绝艺讲解>"
  }
]